baydemir/__init__.py
baydemir/parsing.py
baydemir/py.typed
baydemir-1.0.0.dist-info/LICENSE
baydemir-1.0.0.dist-info/WHEEL
baydemir-1.0.0.dist-info/METADATA
baydemir-1.0.0.dist-info/RECORD
